{
  "ret": true,
  "data": {
    "swiperList": [{
      "id": "0001",
      "imgUrl": "http://img1.qunarzz.com/piao/fusion/1803/5c/969bfa7af00a2702.jpg_750x200_b99b8e07.jpg"
    },{
      "id": "0002",
      "imgUrl": "http://img1.qunarzz.com/piao/fusion/1804/15/9250dbc86a456302.jpg_750x200_b423f532.jpg"
    },{
      "id": "0003",
      "imgUrl": "http://img1.qunarzz.com/piao/fusion/1804/1b/6c766b79e2045102.jpg_750x200_29ad1225.jpg"
    },{
      "id": "0004",
      "imgUrl": "https://imgs.qunarzz.com/piao/fusion/1803/bd/04554e7c67650302.jpg_640x170_a793a191.jpg"
    }],
    "iconList": [{
      "id": "0001",
      "imgUrl": "https://imgs.qunarzz.com/piao/fusion/1606/b3/0249b48a69aaf49a.png",
      "desc": "周边游"
    }, {
      "id": "0002",
      "imgUrl": "https://imgs.qunarzz.com/piao/fusion/1704/fd/7b733d3656f4d002.png",
      "desc": "八达岭长城"
    }, {
      "id": "0003",
      "imgUrl": "https://imgs.qunarzz.com/piao/fusion/1703/5a/612ae0fee636d202.jpg",
      "desc": "故宫"
    }, {
      "id": "0004",
      "imgUrl": "https://imgs.qunarzz.com/piao/fusion/1606/72/65b06c9a1158de9a.png",
      "desc": "古北水镇"
    }, {
      "id": "0005",
      "imgUrl": "https://imgs.qunarzz.com/piao/fusion/1804/53/f7c33a4412d59e02.png",
      "desc": "A+专线"
    }, {
      "id": "0006",
      "imgUrl": "https://imgs.qunarzz.com/piao/fusion/1704/fd/7b733d3656f4d002.png",
      "desc": "必游榜单"
    }, {
      "id": "0007",
      "imgUrl": "https://imgs.qunarzz.com/piao/fusion/1703/5a/612ae0fee636d202.jpg",
      "desc": "演出"
    }, {
      "id": "0008",
      "imgUrl": "https://imgs.qunarzz.com/piao/fusion/1703/5a/612ae0fee636d202.jpg",
      "desc": "城市观光"
    }, {
      "id": "0009",
      "imgUrl": "https://imgs.qunarzz.com/piao/fusion/1606/72/65b06c9a1158de9a.png",
      "desc": "一日游"
    }],
    "listsList": {
      "title": "北京热门景点门票",
      "list": [{
        "id": "0001",
        "imgUrl": "https://imgs.qunarzz.com/sight/p0/1409/19/adca619faaab0898245dc4ec482b5722.jpg_200x200_1bc99086.jpg",
        "title": "故宫门票",
        "desc": ["历史悠久"],
        "evaluateLength": 1232,
        "starlevel": 45,
        "site": "北京·东城区",
        "price": 20
      }, {
        "id": "0002",
        "imgUrl": "https://imgs.qunarzz.com/sight/p0/1708/2b/2b3b94de99c0a425a3.img.jpg_200x200_2458ffb2.jpg",
        "title": "八达岭长城门票",
        "desc": ["万里长城"],
        "evaluateLength": 30234,
        "starlevel": 68,
        "site": "北京·延庆区",
        "price": 25
      }, {
        "id": "0003",
        "imgUrl": "https://imgs.qunarzz.com/sight/p0/1803/7b/7b023b9728f0834fa3.img.jpg_200x200_5fddc1d8.jpg",
        "title": "世界花卉大观园门票",
        "desc": ["醉美花海"],
        "evaluateLength": 4032,
        "starlevel": 87,
        "site": "北京·丰台区",
        "price": 33.1
      }, {
        "id": "0004",
        "imgUrl": "https://imgs.qunarzz.com/sight/p0/1704/d6/d62a708bc69472f5a3.img.jpg_200x200_5193a3b6.jpg",
        "title": "十渡聚龙湾玻璃栈道门票",
        "desc": ["悬空观景"],
        "evaluateLength": 2232,
        "starlevel": 89,
        "site": "北京·十渡风景区",
        "price": 35
      }, {
        "id": "0005",
        "imgUrl": "https://imgs.qunarzz.com/sight/p0/1508/c0/0ddded36771ed10c9e03eb64794610cb.water.jpg_200x200_4d4aaa39.jpg",
        "title": "仙栖洞门票",
        "desc": ["仙美如画"],
        "evaluateLength": 1332,
        "starlevel": 98,
        "site": "北京·房山区",
        "price": 80
      }]
    }
  }
}
